project_name/__init__.py
project_name/subproject/__init__.py
project_name/subproject/myexample.py
project_name/subproject/myexample_nouse.tohelp
project_name/subproject/myexampleb.py
project_name/subproject2/__init__.py
project_name/subproject2/exclude_from_code_coverage.py
project_name/subproject2/myexample2.py
project_name-0.2.175.dist-info/DESCRIPTION.rst
project_name-0.2.175.dist-info/METADATA
project_name-0.2.175.dist-info/RECORD
project_name-0.2.175.dist-info/WHEEL
project_name-0.2.175.dist-info/metadata.json
project_name-0.2.175.dist-info/top_level.txt
