Metadata-Version: 2.0
Name: project-name
Version: 0.2.175
Summary: This a project template including a setup and the generation of sphinx
